TrexCLI-0.0.2a3.dist-info/DESCRIPTION.rst
TrexCLI-0.0.2a3.dist-info/METADATA
TrexCLI-0.0.2a3.dist-info/RECORD
TrexCLI-0.0.2a3.dist-info/WHEEL
TrexCLI-0.0.2a3.dist-info/entry_points.txt
TrexCLI-0.0.2a3.dist-info/metadata.json
TrexCLI-0.0.2a3.dist-info/top_level.txt
trex/__init__.py
trex/main.py
