Metadata-Version: 2.0
Name: TrexCLI
Version: 0.0.2a3
Summary: The Python3 Client for Trex.
Home-page: UNKNOWN
Author: Arc
Author-email: iarunavaofficial@gmail.com
License: UNKNOWN
Keywords: Research
Platform: UNKNOWN
Classifier: Programming Language :: Python :: 3
Classifier: License :: OSI Approved :: MIT License
Classifier: Operating System :: OS Independent
Requires-Dist: pymongo
